[
  {
    "identifier": "portalgun",
    "title": "Portal Gun",
    "description": "Unlocks Portal Gun",
    "icon": "{ForgeCaps:{\"astralsorcery:cap_item_amulet_holder\":{}},id:\"portalgun:item_portalgun\",Count:1b,tag:{lastFired:1b,width:1,channelName:\"Chell\",grabStrength:4,uuid:\"Global\",username:\"Global\",height:2},Damage:0s}",
    "x": 280,
    "y": 165,
    "cost": 250,
    "parents": [],
    "children": [],
    "placed": true
  },
  {
    "identifier": "mega_torch",
    "title": "Mega Torch",
    "description": "Unlocks the Mega Torch",
    "icon": "{id:\"torchmaster:mega_torch\",Count:1,Damage:0s}",
    "x": 354,
    "y": 165,
    "cost": 250,
    "parents": [],
    "children": [],
    "placed": true
  },
  {
    "identifier": "magmaslimedirt",
    "title": "Magma Slime Dirt",
    "description": "Allows the placement of Slime Saplings in Bonsai Pots and further increases speed",
    "icon": "{id:\"tconstruct:slime_dirt\",Count:1,Damage:3s}",
    "x": 333,
    "y": 84,
    "cost": 400,
    "parents": [
      "purpleslimedirt"
    ],
    "children": [],
    "placed": true
  },
  {
    "identifier": "smeltery",
    "title": "Tinkers\u0027 Smeltery",
    "description": "This unlocks the Tinkers\u0027 Construct Smeltery",
    "icon": "{id:\"tconstruct:smeltery_controller\",Count:1b,Damage:0s}",
    "x": 260,
    "y": 134,
    "cost": 100,
    "parents": [],
    "children": [],
    "placed": true
  },
  {
    "identifier": "mystcraft",
    "title": "Mystcraft",
    "description": "it.",
    "icon": "{id:\"mystcraft:page\",Count:1b,tag:{symbol:\"mystcraft:modmat_log2_0\"},Damage:0s}",
    "x": 340,
    "y": 134,
    "cost": 750,
    "parents": [],
    "children": [],
    "placed": true
  },
  {
    "identifier": "redmulch",
    "title": "Red Mulch",
    "description": "Further Increases Bonsai sapling growth speed and droprates",
    "icon": "{id:\"inspirations:mulch\",Count:1,Damage:5s}",
    "x": 333,
    "y": 40,
    "cost": 600,
    "parents": [
      "bluemulch"
    ],
    "children": [
      "rubymulch"
    ],
    "placed": true
  },
  {
    "identifier": "blackmulch",
    "title": "Black Mulch",
    "description": "Further Increases Bonsai sapling growth speed and droprates",
    "icon": "{id:\"inspirations:mulch\",Count:1,Damage:6s}",
    "x": 385,
    "y": -11,
    "cost": 800,
    "parents": [
      "rubymulch"
    ],
    "children": [],
    "placed": true
  },
  {
    "identifier": "bonsai",
    "title": "Bonsai Trees",
    "description": "Unlocks Bonsai Pots to automate Tree Growth",
    "icon": "{id:\"bonsaitrees:bonsaipot\",Count:1,Damage:0s}",
    "x": 260,
    "y": 231,
    "cost": 50,
    "parents": [],
    "children": [],
    "placed": true
  },
  {
    "identifier": "ore_excavation",
    "title": "Ore Excavation",
    "description": "Turns on Ore Excavation",
    "icon": "{ForgeCaps:{\"astralsorcery:cap_item_amulet_holder\":{}},id:\"minecraft:diamond_pickaxe\",Count:1,Damage:0s}",
    "x": 237,
    "y": 197,
    "cost": 500,
    "parents": [],
    "children": [],
    "placed": true
  },
  {
    "identifier": "projecte",
    "title": "ProjectE",
    "description": "This unlocks the ProjectE mod",
    "icon": "{ForgeCaps:{\"astralsorcery:cap_item_amulet_holder\":{}},id:\"projecte:item.pe_transmutation_tablet\",Count:1b,Damage:0s}",
    "x": 302,
    "y": 134,
    "cost": 1000,
    "parents": [],
    "children": [],
    "placed": true
  },
  {
    "identifier": "bluemulch",
    "title": "Blue Mulch",
    "description": "Further Increases Bonsai sapling growth speed and droprates",
    "icon": "{id:\"inspirations:mulch\",Count:1,Damage:7s}",
    "x": 333,
    "y": -11,
    "cost": 500,
    "parents": [
      "ambermulch"
    ],
    "children": [
      "redmulch"
    ],
    "placed": true
  },
  {
    "identifier": "mysticalagradditions",
    "title": "Mystical Agradditions",
    "description": "Unlocks this mod.",
    "icon": "{id:\"mysticalagradditions:insanium\",Count:1b,Damage:0s}",
    "x": 356,
    "y": 197,
    "cost": 1500,
    "parents": [
      "mysticalagriculture"
    ],
    "children": [],
    "placed": true
  },
  {
    "identifier": "blueslimedirt",
    "title": "Blue Slime Dirt",
    "description": "Allows the placement of Slime Saplings in Bonsai Pots",
    "icon": "{id:\"tconstruct:slime_dirt\",Count:1,Damage:1s}",
    "x": 232,
    "y": 84,
    "cost": 200,
    "parents": [],
    "children": [
      "purpleslimedirt"
    ],
    "placed": true
  },
  {
    "identifier": "ambermulch",
    "title": "Amber Mulch",
    "description": "Further Increases Bonsai sapling growth speed and droprates",
    "icon": "{id:\"inspirations:mulch\",Count:1,Damage:3s}",
    "x": 280,
    "y": -11,
    "cost": 400,
    "parents": [
      "yellowmulch"
    ],
    "children": [
      "bluemulch"
    ],
    "placed": true
  },
  {
    "identifier": "purpleslimedirt",
    "title": "Purple Slime Dirt",
    "description": "Allows the placement of Slime Saplings in Bonsai Pots and increases speed",
    "icon": "{id:\"tconstruct:slime_dirt\",Count:1,Damage:2s}",
    "x": 280,
    "y": 84,
    "cost": 300,
    "parents": [
      "blueslimedirt"
    ],
    "children": [
      "magmaslimedirt"
    ],
    "placed": true
  },
  {
    "identifier": "ironjetpacks",
    "title": "Iron Jetpacks",
    "description": "Unlocks Iron Jetpacks",
    "icon": "{ForgeCaps:{\"astralsorcery:cap_item_amulet_holder\":{}},id:\"ironjetpacks:platinum_jetpack\",Count:1,Damage:0s}",
    "x": 237,
    "y": 165,
    "cost": 500,
    "parents": [],
    "children": [],
    "placed": true
  },
  {
    "identifier": "twilightforest",
    "title": "Twilight Forest",
    "description": "Yes.",
    "icon": "{id:\"huntingdim:portal\",Count:1b,Damage:0s}",
    "x": 319,
    "y": 165,
    "cost": 600,
    "parents": [],
    "children": [],
    "placed": true
  },
  {
    "identifier": "fertilesoil",
    "title": "Fertile Soil",
    "description": "Increases Bonsai sapling growth speed and droprates",
    "icon": "{id:\"rustic:fertile_soil\",Count:1,Damage:0s}",
    "x": 232,
    "y": -11,
    "cost": 100,
    "parents": [],
    "children": [
      "brownmulch"
    ],
    "placed": true
  },
  {
    "identifier": "brownmulch",
    "title": "Brown Mulch",
    "description": "Further Increases Bonsai sapling growth speed and droprates",
    "icon": "{id:\"inspirations:mulch\",Count:1,Damage:1s}",
    "x": 232,
    "y": 40,
    "cost": 200,
    "parents": [
      "fertilesoil"
    ],
    "children": [
      "yellowmulch"
    ],
    "placed": true
  },
  {
    "identifier": "rubymulch",
    "title": "Ruby Mulch",
    "description": "Further Increases Bonsai sapling growth speed and droprates",
    "icon": "{id:\"inspirations:mulch\",Count:1,Damage:4s}",
    "x": 385,
    "y": 40,
    "cost": 700,
    "parents": [
      "redmulch"
    ],
    "children": [
      "blackmulch"
    ],
    "placed": true
  },
  {
    "identifier": "mysticalagriculture",
    "title": "Mystical Agriculture",
    "description": "Unlocks Mystical Agriculture",
    "icon": "{id:\"mysticalagriculture:crafting\",Count:1b,Damage:4s}",
    "x": 284,
    "y": 197,
    "cost": 750,
    "parents": [],
    "children": [
      "mysticalagradditions"
    ],
    "placed": true
  },
  {
    "identifier": "yellowmulch",
    "title": "Yellow Mulch",
    "description": "Further Increases Bonsai sapling growth speed and droprates",
    "icon": "{id:\"inspirations:mulch\",Count:1,Damage:2s}",
    "x": 279,
    "y": 40,
    "cost": 300,
    "parents": [
      "brownmulch"
    ],
    "children": [
      "ambermulch"
    ],
    "placed": true
  }
]